LICENSE
gpr_complex/__init__.py
gpr_complex/gaussian_process.py
gpr_complex/kernels.py
gpr_complex/model.py
gpr_complex/plot.py
gpr_complex/py.typed
gpr_complex-0.3.1.dist-info/LICENSE
gpr_complex-0.3.1.dist-info/WHEEL
gpr_complex-0.3.1.dist-info/METADATA
gpr_complex-0.3.1.dist-info/RECORD
