Metadata-Version: 2.1
Name: gpr-complex
Version: 0.3.1
Summary: A GPR library that can work with complex numbers
Home-page: https://github.com/darcamo/gpr_complex
License: MIT
Keywords: GPR,complex
Author: Darlan Cavalcante Moreira
Author-email: darcamo@gmail.com
Requires-Python: >=3.6,<4.0
Classifier: Intended Audience :: Developers
Classifier: Intended Audience :: Science/Research
Classifier: License :: OSI Approved :: MIT License
Classifier: Operating System :: OS Independent
Classifier: Programming Language :: Python :: 3
Classifier: Programming Language :: Python :: 3.6
Classifier: Programming Language :: Python :: 3.7
Classifier: Programming Language :: Python :: 3.8
Classifier: Topic :: Scientific/Engineering
Requires-Dist: bokeh
Requires-Dist: numpy
Requires-Dist: scipy
Project-URL: Repository, https://github.com/darcamo/gpr_complex
